ml_validation/__init__.py
ml_validation/callable/__init__.py
ml_validation/callable/dummy.py
ml_validation/callable/torch.py
ml_validation/database/__init__.py
ml_validation/database/database.py
ml_validation/database/yadisk.py
ml_validation/experiment/__init__.py
ml_validation/experiment/metrics.py
ml_validation/experiment/predict.py
ml_validation/experiment/ptbxl.py
ml_validation/experiment/report.py
ml_validation-0.0.6.dist-info/METADATA
ml_validation-0.0.6.dist-info/WHEEL
ml_validation-0.0.6.dist-info/RECORD
