Metadata-Version: 2.3
Name: ml_validation
Version: 0.0.6
Summary: Package for machine learning validation
Project-URL: Homepage, https://gitlab.com/moskalenkoviktor/ml_validation
Project-URL: Issues, https://gitlab.com/moskalenkoviktor/ml_validation/-/issues
Author-email: Viktor Moskalenko <moskalenkoviktor@list.ru>
Classifier: Operating System :: OS Independent
Classifier: Programming Language :: Python :: 3
Requires-Python: >=3.10
Requires-Dist: numpy<2.0.0,>=1.26.0
Requires-Dist: pandas<3.0.0,>=2.2.0
Requires-Dist: requests<3.0.0,>=2.31.0
Requires-Dist: scikit-learn<2.0.0,>=1.4.0
Requires-Dist: tqdm<5.0.0,>=4.66.0
Provides-Extra: test
Requires-Dist: flake8-pyproject<2.0.0,>=1.2.0; extra == 'test'
Requires-Dist: flake8-quotes<4.0.0,>=3.4.0; extra == 'test'
Requires-Dist: flake8<8.0.0,>=7.0.0; extra == 'test'
Requires-Dist: isort<6.0.0,>=5.13.0; extra == 'test'
Requires-Dist: mypy<2.0.0,>=1.10.0; extra == 'test'
Requires-Dist: nbqa<2.0.0,>=1.8.0; extra == 'test'
Requires-Dist: types-requests<3.0.0,>=2.31.0; extra == 'test'
